sbomify_action/__init__.py
sbomify_action/additional_packages.py
sbomify_action/augmentation.py
sbomify_action/console.py
sbomify_action/enrichment.py
sbomify_action/exceptions.py
sbomify_action/generation.py
sbomify_action/http_client.py
sbomify_action/logging_config.py
sbomify_action/serialization.py
sbomify_action/tool_checks.py
sbomify_action/upload.py
sbomify_action/validation.py
sbomify_action/_augmentation/__init__.py
sbomify_action/_augmentation/metadata.py
sbomify_action/_augmentation/protocol.py
sbomify_action/_augmentation/registry.py
sbomify_action/_augmentation/utils.py
sbomify_action/_augmentation/providers/__init__.py
sbomify_action/_augmentation/providers/bitbucket.py
sbomify_action/_augmentation/providers/github.py
sbomify_action/_augmentation/providers/gitlab.py
sbomify_action/_augmentation/providers/json_config.py
sbomify_action/_augmentation/providers/sbomify_api.py
sbomify_action/_enrichment/__init__.py
sbomify_action/_enrichment/enricher.py
sbomify_action/_enrichment/license_db_generator.py
sbomify_action/_enrichment/license_normalizer.py
sbomify_action/_enrichment/license_utils.py
sbomify_action/_enrichment/lifecycle_data.py
sbomify_action/_enrichment/metadata.py
sbomify_action/_enrichment/protocol.py
sbomify_action/_enrichment/registry.py
sbomify_action/_enrichment/sanitization.py
sbomify_action/_enrichment/utils.py
sbomify_action/_enrichment/sources/__init__.py
sbomify_action/_enrichment/sources/clearlydefined.py
sbomify_action/_enrichment/sources/conan.py
sbomify_action/_enrichment/sources/cratesio.py
sbomify_action/_enrichment/sources/debian.py
sbomify_action/_enrichment/sources/depsdev.py
sbomify_action/_enrichment/sources/ecosystems.py
sbomify_action/_enrichment/sources/license_db.py
sbomify_action/_enrichment/sources/lifecycle.py
sbomify_action/_enrichment/sources/pubdev.py
sbomify_action/_enrichment/sources/purl.py
sbomify_action/_enrichment/sources/pypi.py
sbomify_action/_enrichment/sources/repology.py
sbomify_action-0.13.dist-info/METADATA
sbomify_action-0.13.dist-info/WHEEL
sbomify_action-0.13.dist-info/entry_points.txt
sbomify_action-0.13.dist-info/licenses/LICENSE
sbomify_action-0.13.dist-info/RECORD
