Metadata-Version: 2.3
Name: sbomify-action
Version: 0.13
Summary: Generate, augment, enrich, and manage SBOMs in your CI/CD pipeline
Project-URL: Homepage, https://sbomify.com
Project-URL: Repository, https://github.com/sbomify/github-action
Project-URL: Documentation, https://github.com/sbomify/github-action#readme
Project-URL: Bug Tracker, https://github.com/sbomify/github-action/issues
Project-URL: Changelog, https://github.com/sbomify/github-action/releases
Author-email: sbomify <hello@sbomify.com>
License: Apache-2.0
Keywords: bom,cyclonedx,sbom,security,software-composition-analysis,spdx,supply-chain
Classifier: Development Status :: 4 - Beta
Classifier: Environment :: Console
Classifier: Intended Audience :: Developers
Classifier: Intended Audience :: System Administrators
Classifier: License :: OSI Approved :: Apache Software License
Classifier: Operating System :: OS Independent
Classifier: Programming Language :: Python :: 3
Classifier: Programming Language :: Python :: 3.11
Classifier: Programming Language :: Python :: 3.12
Classifier: Programming Language :: Python :: 3.13
Classifier: Topic :: Security
Classifier: Topic :: Software Development :: Build Tools
Classifier: Topic :: Software Development :: Quality Assurance
Requires-Python: >=3.11
Requires-Dist: conan<3,>=2.0
Requires-Dist: cyclonedx-bom<8,>=7.2.1
Requires-Dist: cyclonedx-python-lib<12,>=11.5.0
Requires-Dist: packageurl-python>=0.17.6
Requires-Dist: questionary<3,>=2.0.1
Requires-Dist: requests<3,>=2.32.3
Requires-Dist: rich>=14.2.0
Requires-Dist: sentry-sdk<3,>=2.21.0
Requires-Dist: spdx-tools>=0.8.3
Requires-Dist: zstandard>=0.25.0
